<?xml version="1.0" encoding="UTF-8"?>
<!DOCTYPE suite SYSTEM "http://testng.org/testng-1.0.dtd">
<suite name="All Test Suite">
    <test verbose="2" preserve-order="true"
          name="Exclude Method Test">
        <classes>
            <class name="tests.C01_Annotations">
                <methods>
<!--                    This will run all methos in the class except "test03"-->
                    <exclude name="test03"> </exclude>
                </methods>
            </class>
        </classes>
    </test>
</suite>